noaatsi.py
noaatsi-0.0.2.dist-info/METADATA
noaatsi-0.0.2.dist-info/WHEEL
noaatsi-0.0.2.dist-info/entry_points.txt
noaatsi-0.0.2.dist-info/top_level.txt
noaatsi-0.0.2.dist-info/RECORD
