Metadata-Version: 2.1
Name: noaatsi
Version: 0.0.2
Summary: A package for displaying TSI graph based on NOAA
Home-page: https://github.com/y-takefuji/noaatsi
Author: yoshiyasu takefuji
Author-email: takefuji@keio.jp
License: UNKNOWN
Project-URL: Bug Tracker, https://github.com/y-takefuji/noaatsi
Platform: UNKNOWN
Classifier: Programming Language :: Python :: 3
Classifier: License :: OSI Approved :: MIT License
Classifier: Operating System :: OS Independent
Requires-Python: >=3.8
